walrus/__init__.py
walrus/api.py
walrus/country.py
walrus/data/__init__.py
walrus/data/country-capitals.csv
vineetbansal_walrus-3.1.0.dist-info/METADATA
vineetbansal_walrus-3.1.0.dist-info/WHEEL
vineetbansal_walrus-3.1.0.dist-info/top_level.txt
vineetbansal_walrus-3.1.0.dist-info/RECORD
