Metadata-Version: 2.4
Name: vineetbansal-walrus
Version: 3.1.0
Summary: Some description here
Author-email: Vineet Bansal <vineetb@princeton.edu>
Classifier: Programming Language :: Python :: 3
Classifier: License :: OSI Approved :: GNU General Public License v3 (GPLv3)
Classifier: Operating System :: POSIX :: Linux
Requires-Python: >=3.10
Provides-Extra: dev
Requires-Dist: black==23.9.1; extra == "dev"
Requires-Dist: pytest; extra == "dev"
Requires-Dist: coveralls; extra == "dev"
Requires-Dist: twine; extra == "dev"
Requires-Dist: flake8; extra == "dev"
